README.rst
setup.py
src/tecthulhu/__init__.py
src/tecthulhu/__main__.py
src/tecthulhu/default-state.yaml
src/tecthulhu.egg-info/PKG-INFO
src/tecthulhu.egg-info/SOURCES.txt
src/tecthulhu.egg-info/dependency_links.txt
src/tecthulhu.egg-info/requires.txt
src/tecthulhu.egg-info/top_level.txt